sasawrapper/__init__.py
sasawrapper/__main__.py
sasawrapper/__version__.py
sasawrapper/sasawrapper.py
sasawrapper/service_control.py
sasawrapper/talker.py
sasawrapper-0.1.0.dist-info/LICENSE
sasawrapper-0.1.0.dist-info/METADATA
sasawrapper-0.1.0.dist-info/WHEEL
sasawrapper-0.1.0.dist-info/top_level.txt
sasawrapper-0.1.0.dist-info/RECORD
