Metadata-Version: 2.1
Name: sasawrapper
Version: 0.1.0
Summary: Wrapper of CeVIO AI
Home-page: https://github.com/takana-v/sasawrapper
Author: takana-v
License: MIT
Platform: UNKNOWN
Classifier: Development Status :: 4 - Beta
Classifier: Environment :: Win32 (MS Windows)
Classifier: License :: OSI Approved :: MIT License
Classifier: Programming Language :: Python :: 3.8
Requires-Dist: pywin32 (>=303)
Provides-Extra: dev
Requires-Dist: pysen[lint] ; extra == 'dev'
Requires-Dist: sphinx ; extra == 'dev'
Requires-Dist: sphinx-rtd-theme ; extra == 'dev'
